LICENSE
README.md
setup.cfg
setup.py
versioneer.py
veris/__init__.py
veris/_version.py
veris/advection.py
veris/area_mass.py
veris/averaging.py
veris/clean_up.py
veris/dynamics_routines.py
veris/dynsolver.py
veris/evp_solver.py
veris/fill_overlap.py
veris/freedrift_solver.py
veris/global_sum.py
veris/growth.py
veris/heat_flux_CESM.py
veris/heat_flux_MITgcm.py
veris/model.py
veris/ocean_stress.py
veris/set_inits.py
veris/settings.py
veris/solve4temp.py
veris/variables.py
veris.egg-info/PKG-INFO
veris.egg-info/SOURCES.txt
veris.egg-info/dependency_links.txt
veris.egg-info/entry_points.txt
veris.egg-info/requires.txt
veris.egg-info/top_level.txt
veris/setup/__init__.py
veris/setup/seaice_global_4deg/__init__.py
veris/setup/seaice_global_4deg/assets.json
veris/setup/seaice_global_4deg/seaice_global_4deg.py