Metadata-Version: 2.1
Name: veris
Version: 0.1.1
Summary: Sea-ice plugin for Veros, the versatile ocean simulator
Home-page: https://veris.readthedocs.io
Author: Jan Gärtner (AWI Bremen)
Author-email: jph.gaertner@gmail.com
License: MIT
Keywords: oceanography python parallel numpy multi-core geophysics ocean-model mpi4py jax
Classifier: Development Status :: 3 - Alpha
Classifier: Intended Audience :: Science/Research
Classifier: License :: OSI Approved :: MIT License
Classifier: Programming Language :: Python :: 3
Classifier: Programming Language :: Python :: 3.7
Classifier: Programming Language :: Python :: 3.8
Classifier: Programming Language :: Python :: 3.9
Classifier: Programming Language :: Python :: 3.10
Classifier: Topic :: Scientific/Engineering
Classifier: Operating System :: Microsoft :: Windows
Classifier: Operating System :: POSIX
Classifier: Operating System :: Unix
Classifier: Operating System :: MacOS
Requires-Python: >=3.7
License-File: LICENSE
